gracedb_sdk/__init__.py
gracedb_sdk/_version.py
gracedb_sdk/api/__init__.py
gracedb_sdk/api/base.py
gracedb_sdk/api/event.py
gracedb_sdk/api/events.py
gracedb_sdk/api/files.py
gracedb_sdk/api/labels.py
gracedb_sdk/api/log.py
gracedb_sdk/api/logs.py
gracedb_sdk/api/tags.py
gracedb_sdk/api/util.py
gracedb_sdk/api/voevents.py
gracedb_sdk-0.2.1.dist-info/licenses/LICENSE.md
gracedb_sdk-0.2.1.dist-info/METADATA
gracedb_sdk-0.2.1.dist-info/WHEEL
gracedb_sdk-0.2.1.dist-info/top_level.txt
gracedb_sdk-0.2.1.dist-info/RECORD
