Metadata-Version: 2.4
Name: gracedb-sdk
Version: 0.2.1
Summary: REST API SDK for GraceDB
Author-email: Leo Singer <leo.p.singer@nasa.gov>
License-Expression: GPL-3.0-or-later
Project-URL: source, https://git.ligo.org/emfollow/gracedb-sdk
Project-URL: Bug Tracker, https://git.ligo.org/emfollow/gracedb-sdk/issues
Project-URL: Documentation, https://gracedb-sdk.readthedocs.io/
Project-URL: Source Code, https://git.ligo.org/emfollow/gracedb-sdk
Classifier: Development Status :: 4 - Beta
Classifier: Environment :: Console
Classifier: Intended Audience :: Science/Research
Classifier: Operating System :: POSIX
Classifier: Programming Language :: Python :: 3
Classifier: Programming Language :: Python :: 3.9
Classifier: Programming Language :: Python :: 3.10
Classifier: Programming Language :: Python :: 3.11
Classifier: Programming Language :: Python :: 3.12
Classifier: Programming Language :: Python :: 3.13
Classifier: Topic :: Internet
Classifier: Topic :: Scientific/Engineering :: Astronomy
Classifier: Topic :: Scientific/Engineering :: Physics
Requires-Python: >=3.9
License-File: LICENSE.md
Requires-Dist: requests-gracedb>=0.2
Provides-Extra: test
Requires-Dist: pytest; extra == "test"
Dynamic: license-file
